MANIFEST.in
README.rst
setup.py
sphinxcontrib/__init__.py
sphinxcontrib/gruffygen.py
sphinxcontrib_gruffygen.egg-info/PKG-INFO
sphinxcontrib_gruffygen.egg-info/SOURCES.txt
sphinxcontrib_gruffygen.egg-info/dependency_links.txt
sphinxcontrib_gruffygen.egg-info/namespace_packages.txt
sphinxcontrib_gruffygen.egg-info/not-zip-safe
sphinxcontrib_gruffygen.egg-info/requires.txt
sphinxcontrib_gruffygen.egg-info/top_level.txt