Metadata-Version: 1.1
Name: sphinxcontrib-gruffygen
Version: 0.1.1
Summary: Gruffy Sphinx extension
Home-page: http://pypi.python.org/pypi/sphinxcontrib-gruffygen/
Author: Hideo Hattori
Author-email: hhatto.jp@gmail.com
License: BSD
Platform: any
Classifier: Development Status :: 3 - Alpha
Classifier: Intended Audience :: Developers
Classifier: License :: OSI Approved :: BSD License
Classifier: Operating System :: OS Independent
Classifier: Programming Language :: Python
Classifier: Topic :: Documentation
Classifier: Topic :: Utilities
